dbfiles/__init__.py
dbfiles/admin.py
dbfiles/apps.py
dbfiles/forms.py
dbfiles/management/__init__.py
dbfiles/management/commands/__init__.py
dbfiles/management/commands/dbfiles_cleanup.py
dbfiles/management/commands/dbfiles_import.py
dbfiles/migrations/0001_initial.py
dbfiles/migrations/__init__.py
dbfiles/models.py
dbfiles/storage.py
dbfiles/urls.py
dbfiles/views.py
django_dbfiles-3.2.0.dist-info/WHEEL
django_dbfiles-3.2.0.dist-info/METADATA
django_dbfiles-3.2.0.dist-info/RECORD
