Metadata-Version: 2.3
Name: django-dbfiles
Version: 3.2.0
Summary: Django storage backend for storing files in your database.
Keywords: django,database,storage,files
Author: Dan Watson
Author-email: Dan Watson <watsond@imsweb.com>
License: BSD
Classifier: Development Status :: 5 - Production/Stable
Classifier: Environment :: Web Environment
Classifier: Framework :: Django
Classifier: Intended Audience :: Developers
Classifier: License :: OSI Approved :: BSD License
Classifier: Operating System :: OS Independent
Classifier: Programming Language :: Python :: 3
Requires-Python: >=3.10
Project-URL: Homepage, https://github.com/imsweb/django-dbfiles
